django_gis_timezones-1.0a3.dist-info/DESCRIPTION.rst
django_gis_timezones-1.0a3.dist-info/METADATA
django_gis_timezones-1.0a3.dist-info/RECORD
django_gis_timezones-1.0a3.dist-info/WHEEL
django_gis_timezones-1.0a3.dist-info/metadata.json
django_gis_timezones-1.0a3.dist-info/top_level.txt
gis_timezones/__init__.py
gis_timezones/managers.py
gis_timezones/models.py
gis_timezones/management/commands/__init__.py
gis_timezones/management/commands/import_timezones.py
gis_timezones/migrations/0001_initial.py
gis_timezones/migrations/__init__.py
