Metadata-Version: 2.0
Name: django-gis-timezones
Version: 1.0a3
Summary: Simple model to save timezones using geo-spatial data
Home-page: https://github.com/marcosgabarda/django-gis-timezones
Author: Marcos Gabarda
Author-email: hey@marcosgabarda.com
License: MIT License
Platform: UNKNOWN
Classifier: Development Status :: 3 - Alpha
Classifier: Environment :: Web Environment
Classifier: Framework :: Django
Classifier: Intended Audience :: Developers
Classifier: License :: OSI Approved :: MIT License
Classifier: Operating System :: OS Independent
Classifier: Programming Language :: Python
Classifier: Programming Language :: Python :: 2
Classifier: Programming Language :: Python :: 3
Classifier: Topic :: Utilities
Requires-Dist: django-belt (>=1.0a1)
Requires-Dist: pyshp (>=1.2.3)
Requires-Dist: requests (>=2.0)
